BCD.v
module BCD(clk, rst_syn, Q, Q_out, Din, load);
input clk;
input rst_syn;
input load;
input Din[3:0];
  output [3:0]  Q; 
  output [7:0]  Q_out; 
  reg [3:0]  Q; 
  reg [7:0]  Q_out; 
always@ (posedge clk )
begin
  if (!rst_syn)
     Q=0;
  else if ( Q == 9)
     Q=0;
  else if (load) 
     Q = Din;
  else 
     Q+=1;
end
  
always@ (*)
 case (Q) 
    4'b0000: Q_out=8'hc0;
    4'b0001: Q_out=8'hf9;
    4'b0010: Q_out=8'ha4;
    4'b0011: Q_out=8'hb0;
    4'b0100: Q_out=8'h99;
    4'b0101: Q_out=8'h92;
    4'b0110: Q_out=8'h82;
    4'b0111: Q_out=8'hf8;
    4'b1000: Q_out=8'h80;
    4'b1001: Q_out=8'h90;
    4'b1010: Q_out=8'ha0;
    4'b1011: Q_out=8'h83;
    4'b1100: Q_out=8'ha7;
    4'b1101: Q_out=8'h91;
    4'b1110: Q_out=8'h84;
    4'b1111: Q_out=8'hf1;
  endcase 
  
 endmodule

BCD_tb.v
`timescale 1ns/1ps
module BCD_tb;
  reg clk;
  reg rst_syn;
  reg Din;
  reg load;
  wire [3:0]  Q; 
  wire [7:0]  Q_out; 
parameter PERIOD = 20;
parameter real DUTY_CYCLE = 0.5;
parameter OFFSET = 0;

initial
    begin
    #OFFSET;
    forever
        begin
        clk = 1'b1;
        #(PERIOD-(PERIOD*DUTY_CYCLE)) clk = 1'b0;
        #(PERIOD*DUTY_CYCLE);
        end
    end
initial begin
    rst_syn = 1'b0;
    #5 rst_syn = 1'b1;
    #195 rst_syn =1'b0;
    #5 rst_syn = 1'b1;
    #55 $finish;
end
initial begin
    load= 1'b0;
    #200 load = 1'b1;
    #10 load = 1'b0;
    #500 $finish;
end
initial begin
    Din= 4'b0001;
    #500 $finish;
end
initial begin
$dumpfile("BCD.vcd");
  $dumpvars(0, BCD_2);
end
  BCD BCD_2 (.clk(clk), .rst_syn(rst_syn), .Din(Din), .Q(Q), .Q_out(Q_out), .load(load));
endmodule

BCD.vcd
$date
	Wed May 04 22:39:17 2022
$end
$version
	Icarus Verilog
$end
$timescale
	1ps
$end
$scope module BCD_tb $end
$scope module BCD_2 $end
$var wire 1 ! Din $end
$var wire 1 " clk $end
$var wire 1 # load $end
$var wire 1 $ rst_syn $end
$var reg 4 % Q [3:0] $end
$var reg 8 & Q_out [7:0] $end
$upscope $end
$upscope $end
$enddefinitions $end
#0
$dumpvars
b11000000 &
b0 %
0$
0#
1"
1!
$end
#5000
1$
#10000
0"
#20000
b11111001 &
b1 %
1"
#30000
0"
#40000
b10100100 &
b10 %
1"
#50000
0"
#60000
b10110000 &
b11 %
1"
#70000
0"
#80000
b10011001 &
b100 %
1"
#90000
0"
#100000
b10010010 &
b101 %
1"
#110000
0"
#120000
b10000010 &
b110 %
1"
#130000
0"
#140000
b11111000 &
b111 %
1"
#150000
0"
#160000
b10000000 &
b1000 %
1"
#170000
0"
#180000
b10010000 &
b1001 %
1"
#190000
0"
#200000
b11000000 &
b0 %
1"
0$
1#
#205000
1$
#210000
0"
0#
#220000
b11111001 &
b1 %
1"
#230000
0"
#240000
b10100100 &
b10 %
1"
#250000
0"
#260000
b10110000 &
b11 %
1"
